irispie/__init__.py
irispie/attributes.py
irispie/contexts.py
irispie/dates.py
irispie/equations.py
irispie/file_io.py
irispie/frames.py
irispie/has_invariant.py
irispie/has_variants.py
irispie/iter_printers.py
irispie/keywords.py
irispie/makers.py
irispie/namings.py
irispie/portables.py
irispie/progress_bars.py
irispie/pyrightconfig.json
irispie/quantities.py
irispie/sources.py
irispie/wrongdoings.py
irispie/aldi/__init__.py
irispie/aldi/adaptations.py
irispie/aldi/differentiators.py
irispie/aldi/finite_differentiators.py
irispie/aldi/invariators.py
irispie/aldi/maps.py
irispie/chartpacks/main.py
irispie/conveniences/__init__.py
irispie/conveniences/copies.py
irispie/conveniences/descriptions.py
irispie/conveniences/flyweights.py
irispie/conveniences/iterators.py
irispie/conveniences/views.py
irispie/databoxes/__init__.py
irispie/databoxes/_exports.py
irispie/databoxes/_fred.py
irispie/databoxes/_imports.py
irispie/databoxes/_imports2.py
irispie/databoxes/_merge.py
irispie/databoxes/_views.py
irispie/databoxes/main.py
irispie/dataslates/__init__.py
irispie/dataslates/_invariants.py
irispie/dataslates/_slatables.py
irispie/dataslates/_variants.py
irispie/dataslates/main.py
irispie/equators/__init__.py
irispie/equators/plain.py
irispie/evaluators/__init__.py
irispie/evaluators/base.py
irispie/executables/__init__.py
irispie/executables/libgcc_s.1.dylib
irispie/executables/libgfortran.3.dylib
irispie/executables/libquadmath.0.dylib
irispie/executables/template.spc
irispie/executables/x12awin.exe
irispie/executables/x13asmac
irispie/executables/x13asunix
irispie/executables/x13aswin.exe
irispie/explanatories/__init__.py
irispie/explanatories/_transforms.py
irispie/explanatories/main.py
irispie/ez_plotly/__init__.py
irispie/ez_plotly/chartboxes.py
irispie/ez_plotly/main.py
irispie/fords/__init__.py
irispie/fords/covariances.py
irispie/fords/descriptors.py
irispie/fords/initializers.py
irispie/fords/kalmans.py
irispie/fords/least_squares.py
irispie-0.68.4.dist-info/METADATA
irispie-0.68.4.dist-info/WHEEL
irispie-0.68.4.dist-info/licenses/LICENCE
irispie-0.68.4.dist-info/RECORD
